README.md
setup.py
tornado_retry_client/__init__.py
tornado_retry_client.egg-info/PKG-INFO
tornado_retry_client.egg-info/SOURCES.txt
tornado_retry_client.egg-info/dependency_links.txt
tornado_retry_client.egg-info/requires.txt
tornado_retry_client.egg-info/top_level.txt