Metadata-Version: 1.0
Name: tornado-retry-client
Version: 0.4.6
Summary: Simple retry tornado http client
Home-page: https://github.com/wpjunior/tornado-retry-client
Author: Wilson Júnior
Author-email: wilsonpjunior@gmail.com
License: MIT
Keywords: tornado retry client
Platform: any
